dafdo/__init__.py
dafdo/compiler.py
dafdo/parser.py
dafdo/utils.py
dafdo-0.7.3.dist-info/METADATA
dafdo-0.7.3.dist-info/WHEEL
dafdo-0.7.3.dist-info/entry_points.txt
dafdo-0.7.3.dist-info/top_level.txt
dafdo-0.7.3.dist-info/RECORD
