Metadata-Version: 2.1
Name: dafdo
Version: 0.7.3
Summary: Dafdo adalah bahasa pemrograman asal indonesia versi bahasa jawa
Home-page: https://pypi.org/project/dafdo/
Author: Daffa Danur Windho
Author-email: danuwindha@gmail.com
